datasette_hello_world/__init__.py
datasette_hello_world-0.1.1.dist-info/METADATA
datasette_hello_world-0.1.1.dist-info/WHEEL
datasette_hello_world-0.1.1.dist-info/entry_points.txt
datasette_hello_world-0.1.1.dist-info/top_level.txt
datasette_hello_world-0.1.1.dist-info/RECORD
