Metadata-Version: 2.1
Name: datasette-hello-world
Version: 0.1.1
Summary: The hello world of Datasette plugins
Home-page: https://github.com/simonw/datasette-hello-world
Author: Simon Willison
License: Apache License, Version 2.0
Project-URL: Issues, https://github.com/simonw/datasette-hello-world/issues
Project-URL: CI, https://github.com/simonw/datasette-hello-world/actions
Project-URL: Changelog, https://github.com/simonw/datasette-hello-world/releases
Platform: UNKNOWN
Requires-Python: >=3.6
Requires-Dist: datasette
Provides-Extra: test
Requires-Dist: pytest ; extra == 'test'
Requires-Dist: pytest-asyncio ; extra == 'test'
